{"id":"yacctqc4757bqrfm9gjghwq","title":"Teachers","desc":"What role should teachers play in the education system?","updated":1655677638692,"created":1655592703613,"custom":{},"fname":"education.teachers","type":"note","vault":{"fsPath":".","selfContained":true,"name":"modernreforms.org"},"contentHash":"add3988726e8af36903af0e00da35efb","links":[],"anchors":{"teacher-behaviortraining":{"type":"header","text":"Teacher Behavior/Training","value":"teacher-behaviortraining","line":8,"column":0,"depth":3}},"children":[],"parent":"xoed3gln7e54djggyzr759v","data":{}}
